iris_client/__init__.py
iris_client/client.py
iris_client/constants.py
iris_client/logger.py
iris_client/py.typed
dioptra_iris_client_elena-0.5.2.dist-info/METADATA
dioptra_iris_client_elena-0.5.2.dist-info/WHEEL
dioptra_iris_client_elena-0.5.2.dist-info/licenses/LICENSE
dioptra_iris_client_elena-0.5.2.dist-info/RECORD
