Metadata-Version: 2.4
Name: dioptra-iris-client-elena
Version: 0.5.2
Summary: Python client for the Iris API.
License: MIT
License-File: LICENSE
Author: Maxime Mouchet
Author-email: maxime.mouchet@lip6.fr
Requires-Python: >=3.9, !=2.7.*, !=3.0.*, !=3.1.*, !=3.2.*, !=3.3.*, !=3.4.*, !=3.5.*, !=3.6.*, !=3.7.*, !=3.8.*
Classifier: License :: OSI Approved :: MIT License
Classifier: Programming Language :: Python :: 3
Classifier: Programming Language :: Python :: 3.10
Classifier: Programming Language :: Python :: 3.11
Classifier: Programming Language :: Python :: 3.12
Classifier: Programming Language :: Python :: 3.13
Classifier: Programming Language :: Python :: 3.14
Requires-Dist: Authlib (>=1.6.4)
Requires-Dist: cryptography (>=44.0.1)
Requires-Dist: httpx (>=0.25.0,<0.26.0)
Project-URL: Homepage, https://github.com/dioptra-io/iris-client
